manual_export/__init__.py
manual_export/enums.py
manual_export/exportInfluxdbEMS.py
manual_export/main.py
manual_export/manual_export_ems.py
manual_export/utils.py
manual_export-1.0.0.dist-info/LICENSE
manual_export-1.0.0.dist-info/METADATA
manual_export-1.0.0.dist-info/WHEEL
manual_export-1.0.0.dist-info/top_level.txt
manual_export-1.0.0.dist-info/RECORD
