Metadata-Version: 2.1
Name: manual_export
Version: 1.0.0
Summary: example package
Author: zhangxh1047
Requires-Python: >=3.8.6
License-File: LICENSE
